pymathnn/__init__.py
pymathnn/activations.py
pymathnn/deactivations.py
pymathnn/matrix.py
pymathnn/tensor.py
pymathnn/interface/__init__.py
pymathnn/interface/matrix.py
tests/__init__.py
tests/test_activations.py
tests/test_deactivations.py
tests/test_matrix.py
tests/test_tensor.py
pymathnn-0.2.9.dist-info/METADATA
pymathnn-0.2.9.dist-info/WHEEL
pymathnn-0.2.9.dist-info/top_level.txt
pymathnn-0.2.9.dist-info/RECORD
