Metadata-Version: 2.1
Name: pymathnn
Version: 0.2.9
Summary: Python module for mathematical operations, matrix manipulations and neural network utilities using NumPy
Author: Daniele Frulla
Author-email: daniele.frulla@newstechnology.eu
Keywords: math numpy matrix neural network ai deep learning algebra cuda cupy transformer machine
Classifier: Programming Language :: Python :: 3
Classifier: Operating System :: OS Independent
Classifier: Intended Audience :: Science/Research
Classifier: Intended Audience :: Developers
Classifier: Topic :: Scientific/Engineering :: Mathematics
Classifier: Topic :: Scientific/Engineering :: Artificial Intelligence
Classifier: Topic :: Software Development :: Libraries :: Python Modules
Classifier: License :: OSI Approved :: MIT License
Requires-Python: >=3.7
Requires-Dist: numpy
